Classfile /C:/Users/77497/.qclaw/workspace/AutoBookkeeper/app/build/tmp/kotlin-classes/debug/com/autobookkeeper/service/PaymentNotificationListener$extractAmount$allDecimals$1.class
  Last modified 2026��5��6��; size 2063 bytes
  SHA-256 checksum 76c63ccd9a1763e04c080b823a98b0b06ff0f9834eecdceac1bfd29ddd8c789e
  Compiled from "PaymentNotificationListener.kt"
final class com.autobookkeeper.service.PaymentNotificationListener$extractAmount$allDecimals$1 extends kotlin.jvm.internal.Lambda implements kotlin.jvm.functions.Function1<kotlin.text.MatchResult, java.lang.Double>
  minor version: 0
  major version: 61
  flags: (0x0030) ACC_FINAL, ACC_SUPER
  this_class: #2                          // com/autobookkeeper/service/PaymentNotificationListener$extractAmount$allDecimals$1
  super_class: #5                         // kotlin/jvm/internal/Lambda
  interfaces: 1, fields: 1, methods: 4, attributes: 5
Constant pool:
   #1 = Utf8               com/autobookkeeper/service/PaymentNotificationListener$extractAmount$allDecimals$1
   #2 = Class              #1             // com/autobookkeeper/service/PaymentNotificationListener$extractAmount$allDecimals$1
   #3 = Utf8               Lkotlin/jvm/internal/Lambda;Lkotlin/jvm/functions/Function1<Lkotlin/text/MatchResult;Ljava/lang/Double;>;
   #4 = Utf8               kotlin/jvm/internal/Lambda
   #5 = Class              #4             // kotlin/jvm/internal/Lambda
   #6 = Utf8               kotlin/jvm/functions/Function1
   #7 = Class              #6             // kotlin/jvm/functions/Function1
   #8 = Utf8               <init>
   #9 = Utf8               ()V
  #10 = Utf8               (I)V
  #11 = NameAndType        #8:#10         // "<init>":(I)V
  #12 = Methodref          #5.#11         // kotlin/jvm/internal/Lambda."<init>":(I)V
  #13 = Utf8               this
  #14 = Utf8               Lcom/autobookkeeper/service/PaymentNotificationListener$extractAmount$allDecimals$1;
  #15 = Utf8               invoke
  #16 = Utf8               (Lkotlin/text/MatchResult;)Ljava/lang/Double;
  #17 = Utf8               Lorg/jetbrains/annotations/Nullable;
  #18 = Utf8               Lorg/jetbrains/annotations/NotNull;
  #19 = Utf8               it
  #20 = String             #19            // it
  #21 = Utf8               kotlin/jvm/internal/Intrinsics
  #22 = Class              #21            // kotlin/jvm/internal/Intrinsics
  #23 = Utf8               checkNotNullParameter
  #24 = Utf8               (Ljava/lang/Object;Ljava/lang/String;)V
  #25 = NameAndType        #23:#24        // checkNotNullParameter:(Ljava/lang/Object;Ljava/lang/String;)V
  #26 = Methodref          #22.#25        // kotlin/jvm/internal/Intrinsics.checkNotNullParameter:(Ljava/lang/Object;Ljava/lang/String;)V
  #27 = Utf8               kotlin/text/MatchResult
  #28 = Class              #27            // kotlin/text/MatchResult
  #29 = Utf8               getGroupValues
  #30 = Utf8               ()Ljava/util/List;
  #31 = NameAndType        #29:#30        // getGroupValues:()Ljava/util/List;
  #32 = InterfaceMethodref #28.#31        // kotlin/text/MatchResult.getGroupValues:()Ljava/util/List;
  #33 = Utf8               java/util/List
  #34 = Class              #33            // java/util/List
  #35 = Utf8               get
  #36 = Utf8               (I)Ljava/lang/Object;
  #37 = NameAndType        #35:#36        // get:(I)Ljava/lang/Object;
  #38 = InterfaceMethodref #34.#37        // java/util/List.get:(I)Ljava/lang/Object;
  #39 = Utf8               java/lang/String
  #40 = Class              #39            // java/lang/String
  #41 = Utf8               ,
  #42 = String             #41            // ,
  #43 = Utf8
  #44 = String             #43            //
  #45 = Utf8               kotlin/text/StringsKt
  #46 = Class              #45            // kotlin/text/StringsKt
  #47 = Utf8               replace$default
  #48 = Utf8               (Ljava/lang/String;Ljava/lang/String;Ljava/lang/String;ZILjava/lang/Object;)Ljava/lang/String;
  #49 = NameAndType        #47:#48        // replace$default:(Ljava/lang/String;Ljava/lang/String;Ljava/lang/String;ZILjava/lang/Object;)Ljava/lang/String;
  #50 = Methodref          #46.#49        // kotlin/text/StringsKt.replace$default:(Ljava/lang/String;Ljava/lang/String;Ljava/lang/String;ZILjava/lang/Object;)Ljava/lang/String;
  #51 = Utf8               toDoubleOrNull
  #52 = Utf8               (Ljava/lang/String;)Ljava/lang/Double;
  #53 = NameAndType        #51:#52        // toDoubleOrNull:(Ljava/lang/String;)Ljava/lang/Double;
  #54 = Methodref          #46.#53        // kotlin/text/StringsKt.toDoubleOrNull:(Ljava/lang/String;)Ljava/lang/Double;
  #55 = Utf8               Lkotlin/text/MatchResult;
  #56 = Utf8               (Ljava/lang/Object;)Ljava/lang/Object;
  #57 = NameAndType        #15:#16        // invoke:(Lkotlin/text/MatchResult;)Ljava/lang/Double;
  #58 = Methodref          #2.#57         // com/autobookkeeper/service/PaymentNotificationListener$extractAmount$allDecimals$1.invoke:(Lkotlin/text/MatchResult;)Ljava/lang/Double;
  #59 = Utf8               p1
  #60 = Utf8               Ljava/lang/Object;
  #61 = Utf8               <clinit>
  #62 = NameAndType        #8:#9          // "<init>":()V
  #63 = Methodref          #2.#62         // com/autobookkeeper/service/PaymentNotificationListener$extractAmount$allDecimals$1."<init>":()V
  #64 = Utf8               INSTANCE
  #65 = NameAndType        #64:#14        // INSTANCE:Lcom/autobookkeeper/service/PaymentNotificationListener$extractAmount$allDecimals$1;
  #66 = Fieldref           #2.#65         // com/autobookkeeper/service/PaymentNotificationListener$extractAmount$allDecimals$1.INSTANCE:Lcom/autobookkeeper/service/PaymentNotificationListener$extractAmount$allDecimals$1;
  #67 = Utf8               Lkotlin/Metadata;
  #68 = Utf8               mv
  #69 = Integer            1
  #70 = Integer            9
  #71 = Integer            0
  #72 = Utf8               k
  #73 = Integer            3
  #74 = Utf8               xi
  #75 = Integer            48
  #76 = Utf8               d1
  #77 = Utf8               \u0000\u0010\n\u0000\n\u0002\u0010\u0006\n\u0000\n\u0002\u0018\u0002\n\u0002\b\u0002\u0010\u0000\u001a\u0004\u0018\u00010\u00012\u0006\u0010\u0002\u001a\u00020\u0003H\n?\u0006\u0004\b\u0004\u0010\u0005
  #78 = Utf8               d2
  #79 = Utf8               <anonymous>
  #80 = Utf8               com/autobookkeeper/service/PaymentNotificationListener
  #81 = Class              #80            // com/autobookkeeper/service/PaymentNotificationListener
  #82 = Utf8               extractAmount
  #83 = NameAndType        #82:#52        // extractAmount:(Ljava/lang/String;)Ljava/lang/Double;
  #84 = Utf8               PaymentNotificationListener.kt
  #85 = Utf8               Code
  #86 = Utf8               LocalVariableTable
  #87 = Utf8               LineNumberTable
  #88 = Utf8               RuntimeInvisibleAnnotations
  #89 = Utf8               RuntimeInvisibleParameterAnnotations
  #90 = Utf8               InnerClasses
  #91 = Utf8               EnclosingMethod
  #92 = Utf8               Signature
  #93 = Utf8               SourceFile
  #94 = Utf8               RuntimeVisibleAnnotations
{
  public static final com.autobookkeeper.service.PaymentNotificationListener$extractAmount$allDecimals$1 INSTANCE;
    descriptor: Lcom/autobookkeeper/service/PaymentNotificationListener$extractAmount$allDecimals$1;
    flags: (0x0019) ACC_PUBLIC, ACC_STATIC, ACC_FINAL

  com.autobookkeeper.service.PaymentNotificationListener$extractAmount$allDecimals$1();
    descriptor: ()V
    flags: (0x0000)
    Code:
      stack=2, locals=1, args_size=1
         0: aload_0
         1: iconst_1
         2: invokespecial #12                 // Method kotlin/jvm/internal/Lambda."<init>":(I)V
         5: return
      LocalVariableTable:
        Start  Length  Slot  Name   Signature
            0       6     0  this   Lcom/autobookkeeper/service/PaymentNotificationListener$extractAmount$allDecimals$1;

  public final java.lang.Double invoke(kotlin.text.MatchResult);
    descriptor: (Lkotlin/text/MatchResult;)Ljava/lang/Double;
    flags: (0x0011) ACC_PUBLIC, ACC_FINAL
    Code:
      stack=6, locals=2, args_size=2
         0: aload_1
         1: ldc           #20                 // String it
         3: invokestatic  #26                 // Method kotlin/jvm/internal/Intrinsics.checkNotNullParameter:(Ljava/lang/Object;Ljava/lang/String;)V
         6: aload_1
         7: invokeinterface #32,  1           // InterfaceMethod kotlin/text/MatchResult.getGroupValues:()Ljava/util/List;
        12: iconst_1
        13: invokeinterface #38,  2           // InterfaceMethod java/util/List.get:(I)Ljava/lang/Object;
        18: checkcast     #40                 // class java/lang/String
        21: ldc           #42                 // String ,
        23: ldc           #44                 // String
        25: iconst_0
        26: iconst_4
        27: aconst_null
        28: invokestatic  #50                 // Method kotlin/text/StringsKt.replace$default:(Ljava/lang/String;Ljava/lang/String;Ljava/lang/String;ZILjava/lang/Object;)Ljava/lang/String;
        31: invokestatic  #54                 // Method kotlin/text/StringsKt.toDoubleOrNull:(Ljava/lang/String;)Ljava/lang/Double;
        34: areturn
      LineNumberTable:
        line 1117: 6
      LocalVariableTable:
        Start  Length  Slot  Name   Signature
            0      35     0  this   Lcom/autobookkeeper/service/PaymentNotificationListener$extractAmount$allDecimals$1;
            0      35     1    it   Lkotlin/text/MatchResult;
    RuntimeInvisibleAnnotations:
      0: #17()
        org.jetbrains.annotations.Nullable
    RuntimeInvisibleParameterAnnotations:
      parameter 0:
        0: #18()
          org.jetbrains.annotations.NotNull

  public java.lang.Object invoke(java.lang.Object);
    descriptor: (Ljava/lang/Object;)Ljava/lang/Object;
    flags: (0x1041) ACC_PUBLIC, ACC_BRIDGE, ACC_SYNTHETIC
    Code:
      stack=2, locals=2, args_size=2
         0: aload_0
         1: aload_1
         2: checkcast     #28                 // class kotlin/text/MatchResult
         5: invokevirtual #58                 // Method invoke:(Lkotlin/text/MatchResult;)Ljava/lang/Double;
         8: areturn
      LineNumberTable:
        line 1117: 0
      LocalVariableTable:
        Start  Length  Slot  Name   Signature
            0       9     0  this   Lcom/autobookkeeper/service/PaymentNotificationListener$extractAmount$allDecimals$1;
            0       9     1    p1   Ljava/lang/Object;

  static {};
    descriptor: ()V
    flags: (0x0008) ACC_STATIC
    Code:
      stack=2, locals=0, args_size=0
         0: new           #2                  // class com/autobookkeeper/service/PaymentNotificationListener$extractAmount$allDecimals$1
         3: dup
         4: invokespecial #63                 // Method "<init>":()V
         7: putstatic     #66                 // Field INSTANCE:Lcom/autobookkeeper/service/PaymentNotificationListener$extractAmount$allDecimals$1;
        10: return
}
InnerClasses:
  static final #2;                        // class com/autobookkeeper/service/PaymentNotificationListener$extractAmount$allDecimals$1
EnclosingMethod: #81.#83                // com.autobookkeeper.service.PaymentNotificationListener.extractAmount
Signature: #3                           // Lkotlin/jvm/internal/Lambda;Lkotlin/jvm/functions/Function1<Lkotlin/text/MatchResult;Ljava/lang/Double;>;
SourceFile: "PaymentNotificationListener.kt"
RuntimeVisibleAnnotations:
  0: #67(#68=[I#69,I#70,I#71],#72=I#73,#74=I#75,#76=[s#77],#78=[s#79,s#43,s#19,s#55,s#15,s#16])
    kotlin.Metadata(
      mv=[1,9,0]
      k=3
      xi=48
      d1=["\u0000\u0010\n\u0000\n\u0002\u0010\u0006\n\u0000\n\u0002\u0018\u0002\n\u0002\b\u0002\u0010\u0000\u001a\u0004\u0018\u00010\u00012\u0006\u0010\u0002\u001a\u00020\u0003H\n?\u0006\u0004\b\u0004\u0010\u0005"]
      d2=["<anonymous>","","it","Lkotlin/text/MatchResult;","invoke","(Lkotlin/text/MatchResult;)Ljava/lang/Double;"]
    )
